furnilytics/__init__.py
furnilytics/__main__.py
furnilytics/client.py
furnilytics-0.1.3.dist-info/METADATA
furnilytics-0.1.3.dist-info/WHEEL
furnilytics-0.1.3.dist-info/top_level.txt
furnilytics-0.1.3.dist-info/RECORD
