Metadata-Version: 2.4
Name: furnilytics
Version: 0.1.3
Summary: Python client for the Furnilytics API (topic/subtopic/dataset).
Author-email: Thijs Meijerink <thijs.meijerink@furnilytics.com>
License: MIT
Project-URL: Homepage, https://www.furnilytics.com
Classifier: Programming Language :: Python :: 3
Classifier: License :: OSI Approved :: MIT License
Classifier: Operating System :: OS Independent
Requires-Python: >=3.9
Requires-Dist: requests>=2.32
Requires-Dist: urllib3>=2.2
Requires-Dist: pandas>=2.0
